<?xml version="1.0" encoding="utf-8"?>
<key id="f0378622-9325-4684-8be6-856988198ac4" version="1">
  <creationDate>2020-09-13T19:59:01.16556Z</creationDate>
  <activationDate>2020-09-13T19:59:01.153879Z</activationDate>
  <expirationDate>2020-12-12T19:59:01.153879Z</expirationDate>
  <descriptor deserializerType="Microsoft.AspNetCore.DataProtection.AuthenticatedEncryption.ConfigurationModel.AuthenticatedEncryptorDescriptorDeserializer, Microsoft.AspNetCore.DataProtection, Version=3.1.4.0, Culture=neutral, PublicKeyToken=adb9793829ddae60">
    <descriptor>
      <encryption algorithm="AES_256_CBC" />
      <validation algorithm="HMACSHA256" />
      <masterKey p4:requiresEncryption="true" xmlns:p4="http://schemas.asp.net/2015/03/dataProtection">
        <!-- Warning: the key below is in an unencrypted form. -->
        <value>FYUzjGR2ZYrOEJTN4IjtshRcq4fwJzG7EcX+UrymEOvxv7JnSQ1kWW5luU0la0kJVQpU4vKRTSJbGfbhTFSHYQ==</value>
      </masterKey>
    </descriptor>
  </descriptor>
</key>